tldr_python/TLDR.py
tldr_python/__init__.py
tldr_python-1.0.0.dist-info/WHEEL
tldr_python-1.0.0.dist-info/METADATA
tldr_python-1.0.0.dist-info/RECORD
