Metadata-Version: 2.1
Name: tldr-python
Version: 1.0.0
Summary: Python wrapper for the TLDR text summarization and analysis API.
Home-page: https://github.com/AmolMavuduru/tldr-python
License: MIT
Keywords: tldr,nlp,artificial intelligence
Author: Amol Mavuduru
Author-email: amolmavuduru@gmail.com
Requires-Python: >=3.7,<4.0
Classifier: License :: OSI Approved :: MIT License
Classifier: Operating System :: OS Independent
Classifier: Programming Language :: Python :: 3
Classifier: Programming Language :: Python :: 3.7
Classifier: Programming Language :: Python :: 3.8
Classifier: Programming Language :: Python :: 3.9
Classifier: Topic :: Scientific/Engineering :: Artificial Intelligence
Classifier: Topic :: Software Development :: Libraries :: Python Modules
Classifier: Topic :: Text Processing :: Linguistic
Requires-Dist: requests (>=2.5,<3.0)
Project-URL: Repository, https://github.com/AmolMavuduru/tldr-python
